
[
    {
        "stagename":"Test2",
        "amount":"4"
    },
    {"humendata":
        [
            {
                "x":-100,
                "y":-100,
                "size":150,
                "checktime":1800,
                "poptime":3000,
                "rmtime":20000
            },
            {
                "x":100,
                "y":20,
                "size":150,
                "checktime":1800,
                "poptime":3000,
                "rmtime":20000
            },
            {
                "x":50,
                "y":-100,
                "size":150,
                "checktime":1800,
                "poptime":3000,
                "rmtime":20000
            },
            {
                "x":0,
                "y":100,
                "size":150,
                "checktime":1800,
                "poptime":3000,
                "rmtime":20000
            }
        ]
    }
]
